src/__init__.py
src/minha_lib.py
pacote_teste_gitaction-0.0.1.dist-info/LICENSE
pacote_teste_gitaction-0.0.1.dist-info/METADATA
pacote_teste_gitaction-0.0.1.dist-info/WHEEL
pacote_teste_gitaction-0.0.1.dist-info/entry_points.txt
pacote_teste_gitaction-0.0.1.dist-info/top_level.txt
pacote_teste_gitaction-0.0.1.dist-info/RECORD
