Metadata-Version: 2.1
Name: pacote-teste-gitaction
Version: 0.0.1
License-File: LICENSE
Requires-Dist: httpx
